CHANGELOG
LICENSE
MANIFEST.in
README.rst
requirements-performance.txt
requirements-runtest.txt
requirements.txt
setup.py
apitest/__init__.py
apitest/__main__.py
apitest.egg-info/PKG-INFO
apitest.egg-info/SOURCES.txt
apitest.egg-info/dependency_links.txt
apitest.egg-info/entry_points.txt
apitest.egg-info/requires.txt
apitest.egg-info/top_level.txt
apitest/actions/__init__.py
apitest/actions/cli.py
apitest/actions/helpers.py
apitest/actions/compare/__init__.py
apitest/actions/compare/api.py
apitest/actions/compare/cli.py
apitest/actions/compare/console.py
apitest/actions/compare/helpers.py
apitest/actions/compare/model.py
apitest/actions/parser/__init__.py
apitest/actions/parser/cli.py
apitest/actions/parser/helpers.py
apitest/actions/parser/model.py
apitest/actions/parser/postman/__init__.py
apitest/actions/parser/postman/api.py
apitest/actions/parser/postman/cli.py
apitest/actions/parser/postman/console.py
apitest/actions/parser/postman/model.py
apitest/actions/parser/postman/parsers.py
apitest/actions/parser/postman/analyze/__init__.py
apitest/actions/parser/postman/analyze/console.py
apitest/actions/parser/postman/analyze/model.py
apitest/actions/parser/postman/parse/__init__.py
apitest/actions/parser/postman/parse/api.py
apitest/actions/parser/postman/parse/console.py
apitest/actions/parser/postman/parse/model.py
apitest/actions/sendto/__init__.py
apitest/actions/sendto/cli.py
apitest/actions/sendto/helpers.py
apitest/actions/sendto/model.py
apitest/actions/sendto/proxy/__init__.py
apitest/actions/sendto/proxy/api.py
apitest/actions/sendto/proxy/console.py
apitest/actions/sendto/proxy/model.py
apitest/actions/unittest/__init__.py
apitest/actions/unittest/cli.py
apitest/actions/unittest/helpers.py
apitest/actions/unittest/analyze/__init__.py
apitest/actions/unittest/analyze/console.py
apitest/actions/unittest/analyze/model.py
apitest/actions/unittest/unittest/__init__.py
apitest/actions/unittest/unittest/api.py
apitest/actions/unittest/unittest/console.py
apitest/actions/unittest/unittest/model.py
apitest/actions/unittest/unittest/attacks/__init__.py
apitest/actions/unittest/unittest/attacks/_conftest.py
